{"backend_name": "ibmq_lima", "backend_version": "1.0.2", "qobj_id": "af83c3e9-d2db-4e19-9bb1-149bb7c7cea3", "job_id": "602cf282c5bbdb05470b2a9e", "success": true, "results": [{"shots": 8192, "success": true, "data": {"counts": {"0x0": 7918, "0x1": 50, "0x10": 44, "0x14": 2, "0x18": 1, "0x2": 36, "0x4": 59, "0x8": 81, "0xa": 1}}, "meas_level": 2, "header": {"clbit_labels": [["c0", 0], ["c0", 1], ["c0", 2], ["c0", 3], ["c0", 4]], "creg_sizes": [["c0", 5]], "global_phase": 0.0, "memory_slots": 5, "n_qubits": 5, "name": "mcalcal_00000", "qreg_sizes": [["q", 5]], "qubit_labels": [["q", 0], ["q", 1], ["q", 2], ["q", 3], ["q", 4]]}, "memory": false}, {"shots": 8192, "success": true, "data": {"counts": {"0x0": 358, "0x1": 7644, "0x10": 4, "0x11": 46, "0x13": 1, "0x19": 2, "0x3": 30, "0x4": 2, "0x5": 26, "0x8": 2, "0x9": 77}}, "meas_level": 2, "header": {"clbit_labels": [["c0", 0], ["c0", 1], ["c0", 2], ["c0", 3], ["c0", 4]], "creg_sizes": [["c0", 5]], "global_phase": 0.0, "memory_slots": 5, "n_qubits": 5, "name": "mcalcal_00001", "qreg_sizes": [["q", 5]], "qubit_labels": [["q", 0], ["q", 1], ["q", 2], ["q", 3], ["q", 4]]}, "memory": false}, {"shots": 8192, "success": true, "data": {"counts": {"0x0": 1516, "0x1": 9, "0x10": 14, "0x12": 34, "0x2": 6465, "0x3": 43, "0x4": 12, "0x5": 1, "0x6": 25, "0x8": 14, "0xa": 58, "0xe": 1}}, "meas_level": 2, "header": {"clbit_labels": [["c0", 0], ["c0", 1], ["c0", 2], ["c0", 3], ["c0", 4]], "creg_sizes": [["c0", 5]], "global_phase": 0.0, "memory_slots": 5, "n_qubits": 5, "name": "mcalcal_00010", "qreg_sizes": [["q", 5]], "qubit_labels": [["q", 0], ["q", 1], ["q", 2], ["q", 3], ["q", 4]]}, "memory": false}, {"shots": 8192, "success": true, "data": {"counts": {"0x0": 66, "0x1": 1508, "0x10": 1, "0x11": 15, "0x12": 1, "0x13": 47, "0x1b": 1, "0x2": 257, "0x3": 6175, "0x5": 7, "0x7": 34, "0x9": 11, "0xa": 2, "0xb": 67}}, "meas_level": 2, "header": {"clbit_labels": [["c0", 0], ["c0", 1], ["c0", 2], ["c0", 3], ["c0", 4]], "creg_sizes": [["c0", 5]], "global_phase": 0.0, "memory_slots": 5, "n_qubits": 5, "name": "mcalcal_00011", "qreg_sizes": [["q", 5]], "qubit_labels": [["q", 0], ["q", 1], ["q", 2], ["q", 3], ["q", 4]]}, "memory": false}, {"shots": 8192, "success": true, "data": {"counts": {"0x0": 521, "0x1": 1, "0x10": 1, "0x14": 58, "0x16": 2, "0x1c": 2, "0x4": 7441, "0x5": 60, "0x6": 33, "0x8": 3, "0xc": 70}}, "meas_level": 2, "header": {"clbit_labels": [["c0", 0], ["c0", 1], ["c0", 2], ["c0", 3], ["c0", 4]], "creg_sizes": [["c0", 5]], "global_phase": 0.0, "memory_slots": 5, "n_qubits": 5, "name": "mcalcal_00100", "qreg_sizes": [["q", 5]], "qubit_labels": [["q", 0], ["q", 1], ["q", 2], ["q", 3], ["q", 4]]}, "memory": false}, {"shots": 8192, "success": true, "data": {"counts": {"0x0": 13, "0x1": 468, "0x10": 1, "0x11": 5, "0x14": 2, "0x15": 30, "0x3": 1, "0x4": 316, "0x5": 7245, "0x6": 5, "0x7": 24, "0x8": 1, "0x9": 6, "0xc": 4, "0xd": 70, "0xf": 1}}, "meas_level": 2, "header": {"clbit_labels": [["c0", 0], ["c0", 1], ["c0", 2], ["c0", 3], ["c0", 4]], "creg_sizes": [["c0", 5]], "global_phase": 0.0, "memory_slots": 5, "n_qubits": 5, "name": "mcalcal_00101", "qreg_sizes": [["q", 5]], "qubit_labels": [["q", 0], ["q", 1], ["q", 2], ["q", 3], ["q", 4]]}, "memory": false}, {"shots": 8192, "success": true, "data": {"counts": {"0x0": 110, "0x1": 1, "0x10": 1, "0x12": 1, "0x14": 5, "0x16": 41, "0x17": 1, "0x2": 390, "0x3": 6, "0x4": 1425, "0x5": 12, "0x6": 6054, "0x7": 50, "0x8": 1, "0xa": 9, "0xc": 18, "0xe": 67}}, "meas_level": 2, "header": {"clbit_labels": [["c0", 0], ["c0", 1], ["c0", 2], ["c0", 3], ["c0", 4]], "creg_sizes": [["c0", 5]], "global_phase": 0.0, "memory_slots": 5, "n_qubits": 5, "name": "mcalcal_00110", "qreg_sizes": [["q", 5]], "qubit_labels": [["q", 0], ["q", 1], ["q", 2], ["q", 3], ["q", 4]]}, "memory": false}, {"shots": 8192, "success": true, "data": {"counts": {"0x0": 5, "0x1": 97, "0x13": 1, "0x14": 1, "0x15": 13, "0x16": 2, "0x17": 41, "0x1f": 2, "0x2": 16, "0x3": 344, "0x4": 51, "0x5": 1406, "0x6": 283, "0x7": 5846, "0xb": 4, "0xc": 1, "0xd": 19, "0xe": 1, "0xf": 59}}, "meas_level": 2, "header": {"clbit_labels": [["c0", 0], ["c0", 1], ["c0", 2], ["c0", 3], ["c0", 4]], "creg_sizes": [["c0", 5]], "global_phase": 0.0, "memory_slots": 5, "n_qubits": 5, "name": "mcalcal_00111", "qreg_sizes": [["q", 5]], "qubit_labels": [["q", 0], ["q", 1], ["q", 2], ["q", 3], ["q", 4]]}, "memory": false}, {"shots": 8192, "success": true, "data": {"counts": {"0x0": 510, "0x1": 4, "0x10": 4, "0x18": 41, "0x2": 1, "0x4": 4, "0x8": 7474, "0x9": 48, "0xa": 30, "0xc": 76}}, "meas_level": 2, "header": {"clbit_labels": [["c0", 0], ["c0", 1], ["c0", 2], ["c0", 3], ["c0", 4]], "creg_sizes": [["c0", 5]], "global_phase": 0.0, "memory_slots": 5, "n_qubits": 5, "name": "mcalcal_01000", "qreg_sizes": [["q", 5]], "qubit_labels": [["q", 0], ["q", 1], ["q", 2], ["q", 3], ["q", 4]]}, "memory": false}, {"shots": 8192, "success": true, "data": {"counts": {"0x0": 22, "0x1": 474, "0x11": 2, "0x18": 3, "0x19": 36, "0x1b": 1, "0x3": 1, "0x5": 1, "0x8": 302, "0x9": 7277, "0xa": 2, "0xb": 28, "0xc": 1, "0xd": 42}}, "meas_level": 2, "header": {"clbit_labels": [["c0", 0], ["c0", 1], ["c0", 2], ["c0", 3], ["c0", 4]], "creg_sizes": [["c0", 5]], "global_phase": 0.0, "memory_slots": 5, "n_qubits": 5, "name": "mcalcal_01001", "qreg_sizes": [["q", 5]], "qubit_labels": [["q", 0], ["q", 1], ["q", 2], ["q", 3], ["q", 4]]}, "memory": false}, {"shots": 8192, "success": true, "data": {"counts": {"0x0": 89, "0x1": 2, "0x10": 1, "0x12": 3, "0x18": 7, "0x1a": 33, "0x1b": 3, "0x2": 413, "0x4": 1, "0x6": 3, "0x8": 1413, "0x9": 7, "0xa": 6129, "0xb": 54, "0xc": 1, "0xd": 1, "0xe": 32}}, "meas_level": 2, "header": {"clbit_labels": [["c0", 0], ["c0", 1], ["c0", 2], ["c0", 3], ["c0", 4]], "creg_sizes": [["c0", 5]], "global_phase": 0.0, "memory_slots": 5, "n_qubits": 5, "name": "mcalcal_01010", "qreg_sizes": [["q", 5]], "qubit_labels": [["q", 0], ["q", 1], ["q", 2], ["q", 3], ["q", 4]]}, "memory": false}, {"shots": 8192, "success": true, "data": {"counts": {"0x0": 4, "0x1": 98, "0x10": 1, "0x13": 2, "0x19": 9, "0x1a": 1, "0x1b": 41, "0x1f": 1, "0x2": 18, "0x3": 353, "0x7": 2, "0x8": 75, "0x9": 1407, "0xa": 272, "0xb": 5875, "0xd": 8, "0xe": 1, "0xf": 24}}, "meas_level": 2, "header": {"clbit_labels": [["c0", 0], ["c0", 1], ["c0", 2], ["c0", 3], ["c0", 4]], "creg_sizes": [["c0", 5]], "global_phase": 0.0, "memory_slots": 5, "n_qubits": 5, "name": "mcalcal_01011", "qreg_sizes": [["q", 5]], "qubit_labels": [["q", 0], ["q", 1], ["q", 2], ["q", 3], ["q", 4]]}, "memory": false}, {"shots": 8192, "success": true, "data": {"counts": {"0x0": 28, "0x14": 2, "0x18": 1, "0x1c": 36, "0x4": 472, "0x5": 7, "0x6": 4, "0x8": 492, "0x9": 6, "0xa": 1, "0xc": 7046, "0xd": 63, "0xe": 34}}, "meas_level": 2, "header": {"clbit_labels": [["c0", 0], ["c0", 1], ["c0", 2], ["c0", 3], ["c0", 4]], "creg_sizes": [["c0", 5]], "global_phase": 0.0, "memory_slots": 5, "n_qubits": 5, "name": "mcalcal_01100", "qreg_sizes": [["q", 5]], "qubit_labels": [["q", 0], ["q", 1], ["q", 2], ["q", 3], ["q", 4]]}, "memory": false}, {"shots": 8192, "success": true, "data": {"counts": {"0x0": 1, "0x1": 23, "0x15": 1, "0x19": 1, "0x1c": 3, "0x1d": 35, "0x4": 15, "0x5": 405, "0x7": 1, "0x8": 25, "0x9": 436, "0xb": 3, "0xc": 292, "0xd": 6928, "0xe": 1, "0xf": 22}}, "meas_level": 2, "header": {"clbit_labels": [["c0", 0], ["c0", 1], ["c0", 2], ["c0", 3], ["c0", 4]], "creg_sizes": [["c0", 5]], "global_phase": 0.0, "memory_slots": 5, "n_qubits": 5, "name": "mcalcal_01101", "qreg_sizes": [["q", 5]], "qubit_labels": [["q", 0], ["q", 1], ["q", 2], ["q", 3], ["q", 4]]}, "memory": false}, {"shots": 8192, "success": true, "data": {"counts": {"0x0": 4, "0x16": 4, "0x18": 1, "0x1a": 4, "0x1c": 6, "0x1e": 31, "0x2": 29, "0x4": 84, "0x6": 330, "0x7": 3, "0x8": 74, "0xa": 408, "0xb": 2, "0xc": 1442, "0xd": 17, "0xe": 5708, "0xf": 45}}, "meas_level": 2, "header": {"clbit_labels": [["c0", 0], ["c0", 1], ["c0", 2], ["c0", 3], ["c0", 4]], "creg_sizes": [["c0", 5]], "global_phase": 0.0, "memory_slots": 5, "n_qubits": 5, "name": "mcalcal_01110", "qreg_sizes": [["q", 5]], "qubit_labels": [["q", 0], ["q", 1], ["q", 2], ["q", 3], ["q", 4]]}, "memory": false}, {"shots": 8192, "success": true, "data": {"counts": {"0x1": 5, "0x13": 1, "0x17": 3, "0x19": 1, "0x1b": 2, "0x1c": 1, "0x1d": 9, "0x1e": 1, "0x1f": 32, "0x3": 32, "0x4": 6, "0x5": 89, "0x6": 9, "0x7": 337, "0x8": 4, "0x9": 97, "0xa": 7, "0xb": 365, "0xc": 59, "0xd": 1336, "0xe": 259, "0xf": 5537}}, "meas_level": 2, "header": {"clbit_labels": [["c0", 0], ["c0", 1], ["c0", 2], ["c0", 3], ["c0", 4]], "creg_sizes": [["c0", 5]], "global_phase": 0.0, "memory_slots": 5, "n_qubits": 5, "name": "mcalcal_01111", "qreg_sizes": [["q", 5]], "qubit_labels": [["q", 0], ["q", 1], ["q", 2], ["q", 3], ["q", 4]]}, "memory": false}, {"shots": 8192, "success": true, "data": {"counts": {"0x0": 850, "0x1": 7, "0x10": 7092, "0x11": 58, "0x12": 31, "0x14": 62, "0x18": 69, "0x19": 1, "0x1a": 1, "0x2": 7, "0x4": 7, "0x8": 7}}, "meas_level": 2, "header": {"clbit_labels": [["c0", 0], ["c0", 1], ["c0", 2], ["c0", 3], ["c0", 4]], "creg_sizes": [["c0", 5]], "global_phase": 0.0, "memory_slots": 5, "n_qubits": 5, "name": "mcalcal_10000", "qreg_sizes": [["q", 5]], "qubit_labels": [["q", 0], ["q", 1], ["q", 2], ["q", 3], ["q", 4]]}, "memory": false}, {"shots": 8192, "success": true, "data": {"counts": {"0x0": 33, "0x1": 877, "0x10": 297, "0x11": 6832, "0x12": 1, "0x13": 21, "0x14": 1, "0x15": 27, "0x18": 3, "0x19": 87, "0x1d": 1, "0x3": 2, "0x5": 2, "0x9": 8}}, "meas_level": 2, "header": {"clbit_labels": [["c0", 0], ["c0", 1], ["c0", 2], ["c0", 3], ["c0", 4]], "creg_sizes": [["c0", 5]], "global_phase": 0.0, "memory_slots": 5, "n_qubits": 5, "name": "mcalcal_10001", "qreg_sizes": [["q", 5]], "qubit_labels": [["q", 0], ["q", 1], ["q", 2], ["q", 3], ["q", 4]]}, "memory": false}, {"shots": 8192, "success": true, "data": {"counts": {"0x0": 186, "0x1": 1, "0x10": 1438, "0x11": 13, "0x12": 5729, "0x13": 41, "0x14": 5, "0x16": 22, "0x18": 17, "0x1a": 69, "0x1c": 1, "0x2": 654, "0x3": 7, "0x6": 2, "0x8": 3, "0xa": 3, "0xb": 1}}, "meas_level": 2, "header": {"clbit_labels": [["c0", 0], ["c0", 1], ["c0", 2], ["c0", 3], ["c0", 4]], "creg_sizes": [["c0", 5]], "global_phase": 0.0, "memory_slots": 5, "n_qubits": 5, "name": "mcalcal_10010", "qreg_sizes": [["q", 5]], "qubit_labels": [["q", 0], ["q", 1], ["q", 2], ["q", 3], ["q", 4]]}, "memory": false}, {"shots": 8192, "success": true, "data": {"counts": {"0x0": 7, "0x1": 190, "0x10": 59, "0x11": 1384, "0x12": 213, "0x13": 5517, "0x14": 2, "0x15": 3, "0x16": 3, "0x17": 31, "0x19": 6, "0x1a": 2, "0x1b": 64, "0x2": 29, "0x3": 667, "0x7": 4, "0x9": 2, "0xa": 1, "0xb": 8}}, "meas_level": 2, "header": {"clbit_labels": [["c0", 0], ["c0", 1], ["c0", 2], ["c0", 3], ["c0", 4]], "creg_sizes": [["c0", 5]], "global_phase": 0.0, "memory_slots": 5, "n_qubits": 5, "name": "mcalcal_10011", "qreg_sizes": [["q", 5]], "qubit_labels": [["q", 0], ["q", 1], ["q", 2], ["q", 3], ["q", 4]]}, "memory": false}, {"shots": 8192, "success": true, "data": {"counts": {"0x0": 50, "0x1": 2, "0x10": 415, "0x11": 3, "0x12": 1, "0x14": 6722, "0x15": 55, "0x16": 33, "0x18": 5, "0x1c": 60, "0x1d": 1, "0x2": 3, "0x4": 831, "0x5": 3, "0x6": 3, "0xc": 5}}, "meas_level": 2, "header": {"clbit_labels": [["c0", 0], ["c0", 1], ["c0", 2], ["c0", 3], ["c0", 4]], "creg_sizes": [["c0", 5]], "global_phase": 0.0, "memory_slots": 5, "n_qubits": 5, "name": "mcalcal_10100", "qreg_sizes": [["q", 5]], "qubit_labels": [["q", 0], ["q", 1], ["q", 2], ["q", 3], ["q", 4]]}, "memory": false}, {"shots": 8192, "success": true, "data": {"counts": {"0x0": 2, "0x1": 56, "0x10": 18, "0x11": 467, "0x13": 1, "0x14": 245, "0x15": 6420, "0x16": 3, "0x17": 17, "0x19": 7, "0x1b": 1, "0x1c": 2, "0x1d": 72, "0x4": 40, "0x5": 827, "0x7": 1, "0x9": 2, "0xd": 11}}, "meas_level": 2, "header": {"clbit_labels": [["c0", 0], ["c0", 1], ["c0", 2], ["c0", 3], ["c0", 4]], "creg_sizes": [["c0", 5]], "global_phase": 0.0, "memory_slots": 5, "n_qubits": 5, "name": "mcalcal_10101", "qreg_sizes": [["q", 5]], "qubit_labels": [["q", 0], ["q", 1], ["q", 2], ["q", 3], ["q", 4]]}, "memory": false}, {"shots": 8192, "success": true, "data": {"counts": {"0x0": 12, "0x10": 80, "0x11": 1, "0x12": 361, "0x13": 6, "0x14": 1315, "0x15": 8, "0x16": 5446, "0x17": 33, "0x1a": 4, "0x1c": 17, "0x1d": 1, "0x1e": 67, "0x1f": 1, "0x2": 41, "0x4": 138, "0x5": 2, "0x6": 644, "0x7": 5, "0xa": 1, "0xe": 9}}, "meas_level": 2, "header": {"clbit_labels": [["c0", 0], ["c0", 1], ["c0", 2], ["c0", 3], ["c0", 4]], "creg_sizes": [["c0", 5]], "global_phase": 0.0, "memory_slots": 5, "n_qubits": 5, "name": "mcalcal_10110", "qreg_sizes": [["q", 5]], "qubit_labels": [["q", 0], ["q", 1], ["q", 2], ["q", 3], ["q", 4]]}, "memory": false}, {"shots": 8192, "success": true, "data": {"counts": {"0x1": 8, "0x10": 3, "0x11": 91, "0x12": 17, "0x13": 331, "0x14": 54, "0x15": 1245, "0x16": 231, "0x17": 5238, "0x19": 1, "0x1b": 2, "0x1d": 9, "0x1e": 2, "0x1f": 59, "0x2": 5, "0x3": 20, "0x4": 6, "0x5": 156, "0x6": 24, "0x7": 677, "0xd": 4, "0xe": 1, "0xf": 8}}, "meas_level": 2, "header": {"clbit_labels": [["c0", 0], ["c0", 1], ["c0", 2], ["c0", 3], ["c0", 4]], "creg_sizes": [["c0", 5]], "global_phase": 0.0, "memory_slots": 5, "n_qubits": 5, "name": "mcalcal_10111", "qreg_sizes": [["q", 5]], "qubit_labels": [["q", 0], ["q", 1], ["q", 2], ["q", 3], ["q", 4]]}, "memory": false}, {"shots": 8192, "success": true, "data": {"counts": {"0x0": 53, "0x1": 1, "0x10": 435, "0x11": 4, "0x12": 5, "0x14": 6, "0x18": 6702, "0x19": 51, "0x1a": 30, "0x1c": 61, "0x1e": 1, "0x8": 825, "0x9": 9, "0xa": 2, "0xc": 7}}, "meas_level": 2, "header": {"clbit_labels": [["c0", 0], ["c0", 1], ["c0", 2], ["c0", 3], ["c0", 4]], "creg_sizes": [["c0", 5]], "global_phase": 0.0, "memory_slots": 5, "n_qubits": 5, "name": "mcalcal_11000", "qreg_sizes": [["q", 5]], "qubit_labels": [["q", 0], ["q", 1], ["q", 2], ["q", 3], ["q", 4]]}, "memory": false}, {"shots": 8192, "success": true, "data": {"counts": {"0x0": 2, "0x1": 47, "0x10": 20, "0x11": 425, "0x13": 1, "0x15": 1, "0x18": 283, "0x19": 6499, "0x1a": 1, "0x1b": 18, "0x1d": 32, "0x5": 1, "0x8": 33, "0x9": 823, "0xb": 3, "0xd": 3}}, "meas_level": 2, "header": {"clbit_labels": [["c0", 0], ["c0", 1], ["c0", 2], ["c0", 3], ["c0", 4]], "creg_sizes": [["c0", 5]], "global_phase": 0.0, "memory_slots": 5, "n_qubits": 5, "name": "mcalcal_11001", "qreg_sizes": [["q", 5]], "qubit_labels": [["q", 0], ["q", 1], ["q", 2], ["q", 3], ["q", 4]]}, "memory": false}, {"shots": 8192, "success": true, "data": {"counts": {"0x0": 7, "0x10": 74, "0x12": 330, "0x13": 3, "0x16": 1, "0x18": 1294, "0x19": 13, "0x1a": 5560, "0x1b": 55, "0x1c": 2, "0x1e": 23, "0x1f": 1, "0x2": 35, "0x8": 141, "0x9": 1, "0xa": 639, "0xb": 10, "0xe": 3}}, "meas_level": 2, "header": {"clbit_labels": [["c0", 0], ["c0", 1], ["c0", 2], ["c0", 3], ["c0", 4]], "creg_sizes": [["c0", 5]], "global_phase": 0.0, "memory_slots": 5, "n_qubits": 5, "name": "mcalcal_11010", "qreg_sizes": [["q", 5]], "qubit_labels": [["q", 0], ["q", 1], ["q", 2], ["q", 3], ["q", 4]]}, "memory": false}, {"shots": 8192, "success": true, "data": {"counts": {"0x0": 1, "0x1": 10, "0x10": 3, "0x11": 76, "0x12": 8, "0x13": 323, "0x15": 1, "0x18": 61, "0x19": 1289, "0x1a": 237, "0x1b": 5254, "0x1d": 3, "0x1f": 16, "0x2": 3, "0x3": 37, "0x8": 6, "0x9": 166, "0xa": 26, "0xb": 668, "0xd": 1, "0xf": 3}}, "meas_level": 2, "header": {"clbit_labels": [["c0", 0], ["c0", 1], ["c0", 2], ["c0", 3], ["c0", 4]], "creg_sizes": [["c0", 5]], "global_phase": 0.0, "memory_slots": 5, "n_qubits": 5, "name": "mcalcal_11011", "qreg_sizes": [["q", 5]], "qubit_labels": [["q", 0], ["q", 1], ["q", 2], ["q", 3], ["q", 4]]}, "memory": false}, {"shots": 8192, "success": true, "data": {"counts": {"0x0": 3, "0x10": 24, "0x14": 372, "0x15": 3, "0x18": 443, "0x1a": 4, "0x1c": 6336, "0x1d": 58, "0x1e": 36, "0x4": 46, "0x8": 70, "0x9": 1, "0xc": 783, "0xd": 9, "0xe": 4}}, "meas_level": 2, "header": {"clbit_labels": [["c0", 0], ["c0", 1], ["c0", 2], ["c0", 3], ["c0", 4]], "creg_sizes": [["c0", 5]], "global_phase": 0.0, "memory_slots": 5, "n_qubits": 5, "name": "mcalcal_11100", "qreg_sizes": [["q", 5]], "qubit_labels": [["q", 0], ["q", 1], ["q", 2], ["q", 3], ["q", 4]]}, "memory": false}, {"shots": 8192, "success": true, "data": {"counts": {"0x1": 4, "0x11": 33, "0x14": 17, "0x15": 383, "0x17": 1, "0x18": 16, "0x19": 401, "0x1b": 1, "0x1c": 280, "0x1d": 6126, "0x1e": 1, "0x1f": 8, "0x4": 3, "0x5": 47, "0x8": 1, "0x9": 60, "0xc": 30, "0xd": 778, "0xf": 2}}, "meas_level": 2, "header": {"clbit_labels": [["c0", 0], ["c0", 1], ["c0", 2], ["c0", 3], ["c0", 4]], "creg_sizes": [["c0", 5]], "global_phase": 0.0, "memory_slots": 5, "n_qubits": 5, "name": "mcalcal_11101", "qreg_sizes": [["q", 5]], "qubit_labels": [["q", 0], ["q", 1], ["q", 2], ["q", 3], ["q", 4]]}, "memory": false}, {"shots": 8192, "success": true, "data": {"counts": {"0x10": 4, "0x12": 19, "0x14": 77, "0x16": 335, "0x17": 3, "0x18": 75, "0x1a": 357, "0x1b": 2, "0x1c": 1208, "0x1d": 11, "0x1e": 5167, "0x1f": 41, "0x2": 2, "0x4": 9, "0x6": 38, "0x8": 14, "0xa": 40, "0xc": 171, "0xe": 612, "0xf": 7}}, "meas_level": 2, "header": {"clbit_labels": [["c0", 0], ["c0", 1], ["c0", 2], ["c0", 3], ["c0", 4]], "creg_sizes": [["c0", 5]], "global_phase": 0.0, "memory_slots": 5, "n_qubits": 5, "name": "mcalcal_11110", "qreg_sizes": [["q", 5]], "qubit_labels": [["q", 0], ["q", 1], ["q", 2], ["q", 3], ["q", 4]]}, "memory": false}, {"shots": 8192, "success": true, "data": {"counts": {"0x10": 1, "0x11": 7, "0x13": 23, "0x14": 4, "0x15": 78, "0x16": 11, "0x17": 294, "0x18": 4, "0x19": 75, "0x1a": 9, "0x1b": 342, "0x1c": 55, "0x1d": 1250, "0x1e": 221, "0x1f": 4930, "0x3": 3, "0x4": 3, "0x5": 6, "0x6": 3, "0x7": 32, "0x9": 10, "0xa": 3, "0xb": 50, "0xc": 5, "0xd": 152, "0xe": 17, "0xf": 604}}, "meas_level": 2, "header": {"clbit_labels": [["c0", 0], ["c0", 1], ["c0", 2], ["c0", 3], ["c0", 4]], "creg_sizes": [["c0", 5]], "global_phase": 0.0, "memory_slots": 5, "n_qubits": 5, "name": "mcalcal_11111", "qreg_sizes": [["q", 5]], "qubit_labels": [["q", 0], ["q", 1], ["q", 2], ["q", 3], ["q", 4]]}, "memory": false}], "date": "2021-02-17 11:59:57+01:00", "status": "Successful completion", "header": {"backend_name": "ibmq_lima", "backend_version": "1.0.2"}, "time_taken": 75.52886939048767, "execution_id": "18f7f1c2-710f-11eb-89bd-b02628f7f59e", "client_version": {"qiskit": "0.23.0"}}